odoo/addons/stock_release_channel_show_weight/README.rst
odoo/addons/stock_release_channel_show_weight/__init__.py
odoo/addons/stock_release_channel_show_weight/__manifest__.py
odoo/addons/stock_release_channel_show_weight/data/decimal_precision.xml
odoo/addons/stock_release_channel_show_weight/i18n/it.po
odoo/addons/stock_release_channel_show_weight/i18n/stock_release_channel_show_weight.pot
odoo/addons/stock_release_channel_show_weight/models/__init__.py
odoo/addons/stock_release_channel_show_weight/models/stock_release_channel.py
odoo/addons/stock_release_channel_show_weight/readme/CONTRIBUTORS.rst
odoo/addons/stock_release_channel_show_weight/readme/DESCRIPTION.rst
odoo/addons/stock_release_channel_show_weight/static/description/icon.png
odoo/addons/stock_release_channel_show_weight/static/description/index.html
odoo/addons/stock_release_channel_show_weight/tests/__init__.py
odoo/addons/stock_release_channel_show_weight/tests/test_channel_computed_fields.py
odoo/addons/stock_release_channel_show_weight/views/release_channel.xml
odoo_addon_stock_release_channel_show_weight-16.0.1.1.0.3.dist-info/METADATA
odoo_addon_stock_release_channel_show_weight-16.0.1.1.0.3.dist-info/WHEEL
odoo_addon_stock_release_channel_show_weight-16.0.1.1.0.3.dist-info/top_level.txt
odoo_addon_stock_release_channel_show_weight-16.0.1.1.0.3.dist-info/RECORD
