Metadata-Version: 2.1
Name: odoo-addon-stock-release-channel-show-weight
Version: 16.0.1.1.0.3
Summary: Display weights of stock release channels
Home-page: https://github.com/OCA/wms
Author: BCIM, Odoo Community Association (OCA)
Author-email: support@odoo-community.org
License: AGPL-3
Platform: UNKNOWN
Classifier: Programming Language :: Python
Classifier: Framework :: Odoo
Classifier: Framework :: Odoo :: 16.0
Classifier: License :: OSI Approved :: GNU Affero General Public License v3
Requires-Python: >=3.10
Requires-Dist: odoo-addon-stock-release-channel <16.1dev,>=16.0dev
Requires-Dist: odoo <16.1dev,>=16.0a
